etsy_python/__init__.py
etsy_python/_version.py
etsy_python/v3/__init__.py
etsy_python/v3/auth/OAuth.py
etsy_python/v3/auth/__init__.py
etsy_python/v3/common/Env.py
etsy_python/v3/common/Request.py
etsy_python/v3/common/Utils.py
etsy_python/v3/common/__init__.py
etsy_python/v3/enums/HolidayPreferences.py
etsy_python/v3/enums/Language.py
etsy_python/v3/enums/Listing.py
etsy_python/v3/enums/ListingInventory.py
etsy_python/v3/enums/ShippingProfile.py
etsy_python/v3/enums/ShopReceipt.py
etsy_python/v3/enums/__init__.py
etsy_python/v3/exceptions/BaseAPIException.py
etsy_python/v3/exceptions/RequestException.py
etsy_python/v3/exceptions/__init__.py
etsy_python/v3/models/FileRequest.py
etsy_python/v3/models/HolidayPreferences.py
etsy_python/v3/models/Listing.py
etsy_python/v3/models/Miscellaneous.py
etsy_python/v3/models/Product.py
etsy_python/v3/models/Receipt.py
etsy_python/v3/models/Request.py
etsy_python/v3/models/ShippingProfile.py
etsy_python/v3/models/Shop.py
etsy_python/v3/models/ShopReturnPolicy.py
etsy_python/v3/models/Utils.py
etsy_python/v3/models/__init__.py
etsy_python/v3/resources/HolidayPreferences.py
etsy_python/v3/resources/Listing.py
etsy_python/v3/resources/ListingFile.py
etsy_python/v3/resources/ListingImage.py
etsy_python/v3/resources/ListingInventory.py
etsy_python/v3/resources/ListingOffering.py
etsy_python/v3/resources/ListingProduct.py
etsy_python/v3/resources/ListingTranslation.py
etsy_python/v3/resources/ListingVariationImages.py
etsy_python/v3/resources/ListingVideo.py
etsy_python/v3/resources/Miscellaneous.py
etsy_python/v3/resources/Payment.py
etsy_python/v3/resources/PaymentLedgerEntry.py
etsy_python/v3/resources/Receipt.py
etsy_python/v3/resources/ReceiptTransactions.py
etsy_python/v3/resources/Response.py
etsy_python/v3/resources/Review.py
etsy_python/v3/resources/Session.py
etsy_python/v3/resources/ShippingProfile.py
etsy_python/v3/resources/Shop.py
etsy_python/v3/resources/ShopProductionPartner.py
etsy_python-1.0.20.dist-info/LICENSE
etsy_python-1.0.20.dist-info/METADATA
etsy_python-1.0.20.dist-info/WHEEL
etsy_python-1.0.20.dist-info/top_level.txt
etsy_python-1.0.20.dist-info/RECORD
