Metadata-Version: 2.1
Name: etsy-python
Version: 1.0.20
Summary: Etsy API Client Library for Python
Author: Amit Ray
Author-email: mail@amitray.dev
Project-URL: Documentation, https://github.com/amitray007/etsy-python-sdk/blob/master/README.md
Project-URL: Source code, https://github.com/amitray007/etsy-python-sdk
Project-URL: Issues, https://github.com/amitray007/etsy-python-sdk/issues
Keywords: python,etsy,api
Classifier: Intended Audience :: Developers
Classifier: Programming Language :: Python :: 3
Classifier: Operating System :: Unix
Classifier: Operating System :: MacOS :: MacOS X
Classifier: Operating System :: Microsoft :: Windows
License-File: LICENSE
Requires-Dist: requests
Requires-Dist: requests-oauthlib
